<?xml version="1.0" encoding="utf-8" ?>
<dwsync>
<file name="lil.png" server="E:/LeHungTin/LHT-Web/cuoiki2/cuoiky_server/" local="132827246000122150" remote="132827246000000000" Dst="0" />
<file name="harley.png" server="E:/LeHungTin/LHT-Web/cuoiki2/cuoiky_server/" local="132827240925769016" remote="132827240920000000" Dst="0" />
<file name="nikola.png" server="E:/LeHungTin/LHT-Web/cuoiki2/cuoiky_server/" local="132827241124925450" remote="132827241120000000" Dst="0" />
<file name="noodles.png" server="E:/LeHungTin/LHT-Web/cuoiki2/cuoiky_server/" local="132827241035659288" remote="132827241030000000" Dst="0" />
<file name="stewart.png" server="E:/LeHungTin/LHT-Web/cuoiki2/cuoiky_server/" local="132827241217531248" remote="132827241210000000" Dst="0" />
<file name="facebook-logo-white.png" server="E:/LeHungTin/LHT-Web/cuoiki2/cuoiky_server/" local="132826490689178918" remote="132826490680000000" Dst="0" />
<file name="instaa.png" server="E:/LeHungTin/LHT-Web/cuoiki2/cuoiky_server/" local="132826501190948554" remote="132826501190000000" Dst="0" />
<file name="unnamed.png" server="E:/LeHungTin/LHT-Web/cuoiki2/cuoiky_server/" local="132826502123103130" remote="132826502120000000" Dst="0" />
<file name="phone.png" server="E:/LeHungTin/LHT-Web/cuoiki2/cuoiky_server/" local="132826704561794948" remote="132826704560000000" Dst="0" />
<file name="web.png" server="E:/LeHungTin/LHT-Web/cuoiki2/cuoiky_server/" local="132826701305433907" remote="132826701300000000" Dst="0" />
<file name="home.png" server="E:/LeHungTin/LHT-Web/cuoiki2/cuoiky_server/" local="132826701516846683" remote="132826701510000000" Dst="0" />
</dwsync>